LICENSE
awscliv2/__init__.py
awscliv2/__main__.py
awscliv2/api.py
awscliv2/cli_parser.py
awscliv2/constants.py
awscliv2/exceptions.py
awscliv2/installers.py
awscliv2/interactive_process.py
awscliv2/logger.py
awscliv2/main.py
awscliv2/py.typed
awscliv2-2.3.0.dist-info/LICENSE
awscliv2-2.3.0.dist-info/METADATA
awscliv2-2.3.0.dist-info/WHEEL
awscliv2-2.3.0.dist-info/entry_points.txt
awscliv2-2.3.0.dist-info/RECORD
