Metadata-Version: 2.1
Name: awscliv2
Version: 2.3.0
Summary: Wrapper for AWS CLI v2
Home-page: https://youtype.github.io/awscliv2/
License: MIT
Keywords: awscli,awscliv2,wrapper
Author: Vlad Emelianov
Author-email: vlad.emelianov.nz@gmail.com
Requires-Python: >=3.7,<4.0
Classifier: Development Status :: 5 - Production/Stable
Classifier: Environment :: Console
Classifier: Intended Audience :: Developers
Classifier: License :: OSI Approved :: MIT License
Classifier: Natural Language :: English
Classifier: Operating System :: OS Independent
Classifier: Programming Language :: Python :: 3
Classifier: Programming Language :: Python :: 3.7
Classifier: Programming Language :: Python :: 3.8
Classifier: Programming Language :: Python :: 3.9
Classifier: Programming Language :: Python :: 3.10
Classifier: Programming Language :: Python :: 3.11
Classifier: Programming Language :: Python :: 3.12
Classifier: Programming Language :: Python :: 3 :: Only
Classifier: Programming Language :: Python :: 3.13
Classifier: Programming Language :: Python :: Implementation :: CPython
Classifier: Topic :: Software Development :: Libraries :: Python Modules
Classifier: Typing :: Typed
Requires-Dist: importlib-metadata ; python_version < "3.8"
Requires-Dist: pip
Project-URL: Bug Tracker, https://github.com/youtype/awscliv2/issues
Project-URL: Documentation, https://awscliv2.readthedocs.io/en/latest/
Project-URL: Repository, https://github.com/youtype/awscliv2
Project-URL: Source, https://github.com/youtype/awscliv2
